kwiver-1.4.6.dist-info/RECORD
kwiver-1.4.6.dist-info/WHEEL
kwiver-1.4.6.dist-info/top_level.txt
kwiver-1.4.6.dist-info/METADATA
kwiver-1.4.6.dist-info/entry_points.txt
sprokit/__init__.py
sprokit/schedulers/__init__.py
sprokit/processes/__init__.py
sprokit/pipeline/__init__.py
sprokit/pipeline_util/__init__.py
sprokit/tests/__init__.py
sprokit/tests/processes/__init__.py
kwiver/log4cxx.properties
kwiver/kwiver_tools.py
kwiver/log4cplus.properties
kwiver/__init__.py
kwiver/lib/libvital_vpm.so.1.4.0
kwiver/lib/libvital_algo.so.1.4.0
kwiver/lib/libvital_vpm.so
kwiver/lib/libvital_algo.so
kwiver/lib/kwiver/processes/schedulers.so
kwiver/lib/kwiver/processes/processes_flow.so
kwiver/lib/kwiver/processes/schedulers_examples.so
kwiver/lib/kwiver/processes/template_processes.so
kwiver/lib/kwiver/processes/kwiver_epx_test.so
kwiver/lib/kwiver/processes/processes_clusters.so
kwiver/lib/kwiver/processes/kwiver_processes.so
kwiver/lib/kwiver/processes/kwiver_processes_adapter.so
kwiver/lib/kwiver/processes/kwiver_processes_ocv.so
kwiver/lib/kwiver/processes/kwiver_processes_transport.so
kwiver/lib/kwiver/processes/processes_examples.so
kwiver/lib/kwiver/modules/kwiver_algo_core_plugin.so
kwiver/lib/kwiver/modules/kwiver_algo_ffmpeg_plugin.so
kwiver/lib/kwiver/modules/kwiver_algo_ocv_plugin.so
kwiver/lib/kwiver/modules/vital_log4cplus_logger.so
kwiver/lib/kwiver/modules/kwiver_serialize_json_plugin.so
kwiver/lib/kwiver/modules/modules_python.so
kwiver/lib/kwiver/modules/kwiver_algo_kpf_plugin.so
kwiver/lib/kwiver/modules/kwiver_serialize_protobuf_plugin.so
kwiver/lib/kwiver/modules/format_config.so
kwiver/lib/kwiver/modules/applets/kwiver_algo_core_applets.so
kwiver/lib/kwiver/modules/applets/vital_applets.so
kwiver/lib/kwiver/modules/applets/sprokit_applets.so
kwiver/lib/kwiver/modules/plugin_explorer/process_explorer_plugin.so
kwiver/lib/kwiver/modules/plugin_explorer/algo_explorer_plugin.so
kwiver/lib/pkgconfig/sprokit-pipeline.pc
kwiver/lib/pkgconfig/sprokit-pipeline_util.pc
kwiver/sprokit/sprokit_logging.py
kwiver/sprokit/__init__.py
kwiver/sprokit/schedulers/pythread_per_process.py
