Metadata-Version: 2.1
Name: kwiver
Version: 1.4.6
Summary: Python and C++ toolkit that pulls together computer vision algorithms  into highly modular run time configurable systems
Home-page: https://github.com/Kitware/kwiver
Author: Kitware, Inc.
Author-email: kwiver-developers@kitware.com
License: BSD 3-Clause
Platform: linux
Platform: Unix
Classifier: Intended Audience :: Developers
Classifier: Intended Audience :: Science/Research
Classifier: License :: OSI Approved :: BSD License
Classifier: Programming Language :: Python :: 3.5
Classifier: Programming Language :: Python :: 3.6
Classifier: Programming Language :: Python :: 3.7
Classifier: Programming Language :: Python :: 3.8
Classifier: Operating System :: Unix
Classifier: Topic :: Scientific/Engineering :: Artificial Intelligence
Requires-Python: >=3.5
Requires-Dist: numpy
Requires-Dist: pillow
Requires-Dist: six
